Metadata-Version: 1.0
Name: canonicalwebteam.views-from-yaml
Version: 0.2.2
Summary: A helper function for creating Django views from a YAML file of URL paths
Home-page: https://github.com/canonical-webteam/views-from-yaml
Author: Canonical webteam
Author-email: robin+pypi@canonical.com
License: UNKNOWN
Platform: UNKNOWN
